abuse_whois/__init__.py
abuse_whois/errors.py
abuse_whois/main.py
abuse_whois/settings.py
abuse_whois/utils.py
abuse_whois/whois.py
abuse_whois/api/__init__.py
abuse_whois/api/main.py
abuse_whois/api/endpoints/__init__.py
abuse_whois/api/endpoints/index.py
abuse_whois/api/endpoints/whois.py
abuse_whois/matchers/__init__.py
abuse_whois/matchers/shared_hosting/__init__.py
abuse_whois/matchers/shared_hosting/rules/000webhost.yaml
abuse_whois/matchers/shared_hosting/rules/adobe.yaml
abuse_whois/matchers/shared_hosting/rules/backblaze.yaml
abuse_whois/matchers/shared_hosting/rules/bitly.yaml
abuse_whois/matchers/shared_hosting/rules/blogger.yaml
abuse_whois/matchers/shared_hosting/rules/changeip.yaml
abuse_whois/matchers/shared_hosting/rules/cloudflare.yaml
abuse_whois/matchers/shared_hosting/rules/firebase.yaml
abuse_whois/matchers/shared_hosting/rules/glitch.yaml
abuse_whois/matchers/shared_hosting/rules/godaddy.yaml
abuse_whois/matchers/shared_hosting/rules/google_cloud.yaml
abuse_whois/matchers/shared_hosting/rules/google_site.yaml
abuse_whois/matchers/shared_hosting/rules/jimdo.yaml
abuse_whois/matchers/shared_hosting/rules/micorosoft.yaml
abuse_whois/matchers/shared_hosting/rules/netlify.yaml
abuse_whois/matchers/shared_hosting/rules/notion.yaml
abuse_whois/matchers/shared_hosting/rules/replit.yaml
abuse_whois/matchers/shared_hosting/rules/softlayer.yaml
abuse_whois/matchers/shared_hosting/rules/square.yaml
abuse_whois/matchers/shared_hosting/rules/telegram.yaml
abuse_whois/matchers/shared_hosting/rules/weebly.yaml
abuse_whois/matchers/shared_hosting/rules/wordpress.yaml
abuse_whois/matchers/shared_hosting/rules/yola.yaml
abuse_whois/matchers/whois/__init__.py
abuse_whois/matchers/whois/rules/alibaba_cloud.yaml
abuse_whois/matchers/whois/rules/cloudflare.yaml
abuse_whois/matchers/whois/rules/digitalocean.yaml
abuse_whois/matchers/whois/rules/dynadot.yaml
abuse_whois/matchers/whois/rules/fran_tech.yaml
abuse_whois/matchers/whois/rules/gname.yaml
abuse_whois-0.10.2.dist-info/METADATA
abuse_whois-0.10.2.dist-info/WHEEL
abuse_whois-0.10.2.dist-info/entry_points.txt
abuse_whois-0.10.2.dist-info/licenses/LICENSE
abuse_whois-0.10.2.dist-info/RECORD
