Metadata-Version: 2.4
Name: abuse-whois
Version: 0.10.2
Summary: Find where to report a domain for abuse
Project-URL: Homepage, https://github.com/ninoseki/abuse_whois
Project-URL: Repository, https://github.com/ninoseki/abuse_whois
Author-email: Manabu Niseki <manabu.niseki@gmail.com>
License-Expression: MIT
License-File: LICENSE
Requires-Python: <3.13,>=3.10
Requires-Dist: aiometer~=0.5
Requires-Dist: asyncache~=0.3
Requires-Dist: asyncer>=0.0.8
Requires-Dist: asyncwhois~=1.1
Requires-Dist: azuma~=0.7
Requires-Dist: cachetools~=5.5
Requires-Dist: loguru~=0.7
Requires-Dist: pydantic!=2.1.0,<3.0.0,>2.0.1
Requires-Dist: pyyaml~=6.0
Requires-Dist: returns~=0.24
Requires-Dist: stamina~=24.3
Requires-Dist: starlette<0.46.0,>=0.40.0
Requires-Dist: tld~=0.13
Requires-Dist: validators~=0.34
Provides-Extra: api
Requires-Dist: fastapi[all]~=0.115; extra == 'api'
Requires-Dist: gunicorn~=23.0; extra == 'api'
